[
    { "id": "a1",  "title": "科学館で体験エリア巡り",       "tags": ["indoor","learning","kids"],   "duration": 90  },
    { "id": "a2",  "title": "河川敷サイクリング",           "tags": ["outdoor","refresh","active"], "duration": 120 },
    { "id": "a3",  "title": "商店街で食べ歩き",             "tags": ["outdoor","food","walk"],      "duration": 60  },
  
    { "id": "a4",  "title": "近所の公園でピクニック",       "tags": ["outdoor","nature","budget"],  "duration": 90  },
    { "id": "a5",  "title": "図書館でのんびり読書",         "tags": ["indoor","relax","free"],      "duration": 60  },
    { "id": "a6",  "title": "美術館の企画展を観る",         "tags": ["indoor","learning","relax"],  "duration": 90  },
    { "id": "a7",  "title": "海辺を散歩して写真撮影",       "tags": ["outdoor","refresh","walk"],   "duration": 75  },
    { "id": "a8",  "title": "植物園で季節の花めぐり",       "tags": ["outdoor","nature","relax"],   "duration": 80  },
    { "id": "a9",  "title": "手作りピザに挑戦",             "tags": ["indoor","food","learning"],   "duration": 90  },
    { "id": "a10", "title": "ボードゲームカフェで遊ぶ",     "tags": ["indoor","relax"],             "duration": 120 },
  
    { "id": "a11", "title": "朝のジョギング",               "tags": ["outdoor","refresh","active"], "duration": 30  },
    { "id": "a12", "title": "川沿いでスケッチ",             "tags": ["outdoor","relax","nature"],   "duration": 60  },
    { "id": "a13", "title": "パン屋さんでモーニング",       "tags": ["indoor","food","refresh"],    "duration": 45  },
    { "id": "a14", "title": "家庭菜園の手入れ",             "tags": ["outdoor","nature","refresh"], "duration": 50  },
    { "id": "a15", "title": "プラモデル制作",               "tags": ["indoor","craft","relax"],     "duration": 120 },
    { "id": "a16", "title": "手帳タイム（計画・振り返り）", "tags": ["indoor","relax"],             "duration": 40  },
    { "id": "a17", "title": "近場の温浴施設でゆったり",     "tags": ["indoor","relax"],             "duration": 120 },
    { "id": "a18", "title": "公園でシャボン玉",             "tags": ["outdoor","kids","budget"],    "duration": 40  },
    { "id": "a19", "title": "商店街の八百屋巡り",           "tags": ["outdoor","walk","budget"],    "duration": 60  },
    { "id": "a20", "title": "室内ヨガ・ストレッチ",         "tags": ["indoor","refresh","relax"],   "duration": 30  },
  
    { "id": "a21", "title": "子どもと工作（紙コップけん玉）","tags": ["indoor","kids","craft"],     "duration": 25  },
    { "id": "a22", "title": "展望台から街並みを眺める",     "tags": ["outdoor","refresh"],          "duration": 45  },
    { "id": "a23", "title": "動物園でのんびり一周",         "tags": ["outdoor","nature","kids"],    "duration": 120 },
    { "id": "a24", "title": "カフェで作業（はかどる時間）", "tags": ["indoor","relax"],             "duration": 90  },
    { "id": "a25", "title": "市場・道の駅で食べ歩き",       "tags": ["outdoor","food","walk"],      "duration": 70  },
    { "id": "a26", "title": "歴史的建造物を巡る",           "tags": ["outdoor","learning","walk"],  "duration": 90  },
    { "id": "a27", "title": "天体観測の準備＆星空観察",     "tags": ["outdoor","learning","nature"],"duration": 120 },
    { "id": "a28", "title": "お弁当づくり",                 "tags": ["indoor","food","budget"],     "duration": 60  },
    { "id": "a29", "title": "フリマ/リサイクルショップ巡り","tags": ["outdoor","walk","budget"],    "duration": 80  },
    { "id": "a30", "title": "音楽フェス/路上ライブを聴く", "tags": ["outdoor","refresh"],          "duration": 90  },
  
    { "id": "a31", "title": "家で映画鑑賞会",               "tags": ["indoor","relax"],             "duration": 120 },
    { "id": "a32", "title": "写真の現像・アルバム作成",     "tags": ["indoor","craft","relax"],     "duration": 60  },
    { "id": "a33", "title": "パン作り体験教室",             "tags": ["indoor","learning","food"],   "duration": 120 },
    { "id": "a34", "title": "公園で凧あげ",                 "tags": ["outdoor","refresh","kids"],   "duration": 60  },
    { "id": "a35", "title": "川原で石拾い＆水切り",         "tags": ["outdoor","nature","walk"],    "duration": 50  },
    { "id": "a36", "title": "近所の神社でお参り＆散策",     "tags": ["outdoor","walk","relax"],     "duration": 40  },
    { "id": "a37", "title": "DIYで棚を作る/修理する",       "tags": ["indoor","craft","learning"],  "duration": 120 },
    { "id": "a38", "title": "ソロ喫茶店巡り（梯子）",       "tags": ["indoor","food","walk"],       "duration": 90  },
    { "id": "a39", "title": "朝市で新鮮野菜を買う",         "tags": ["outdoor","budget","walk"],    "duration": 45  },
    { "id": "a40", "title": "河原で読書＆コーヒー",         "tags": ["outdoor","relax","nature"],   "duration": 70  },
    { "id": "a41", "title": "公園でキャッチボール",        "tags": ["outdoor","kids","refresh"],    "duration": 60 },
    { "id": "a42", "title": "水鉄砲バトル",                "tags": ["outdoor","kids","refresh"],    "duration": 45 },
    { "id": "a43", "title": "おうちで宝探しゲーム",        "tags": ["indoor","kids","budget"],      "duration": 40 },
    { "id": "a44", "title": "折り紙で大作づくり",          "tags": ["indoor","kids","craft"],       "duration": 50 },
    { "id": "a45", "title": "お菓子作り（クッキー型抜き）","tags": ["indoor","kids","food"],        "duration": 70 },
    { "id": "a46", "title": "砂場でトンネル作り",          "tags": ["outdoor","kids","nature"],     "duration": 60 },
    { "id": "a47", "title": "段ボールで秘密基地作り",      "tags": ["indoor","kids","craft"],       "duration": 90 },
    { "id": "a48", "title": "子どもと図書館のおはなし会",  "tags": ["indoor","kids","learning"],    "duration": 45 },
    { "id": "a49", "title": "昆虫採集",                    "tags": ["outdoor","kids","nature"],     "duration": 80 },
    { "id": "a50", "title": "紙飛行機大会",                "tags": ["indoor","kids","craft"],       "duration": 30 },

    { "id": "a51", "title": "動物園で餌やり体験",          "tags": ["outdoor","kids","nature"],     "duration": 120 },
    { "id": "a52", "title": "水族館でイルカショー観賞",    "tags": ["indoor","kids","learning"],    "duration": 100 },
    { "id": "a53", "title": "親子でプラネタリウム",        "tags": ["indoor","kids","learning"],    "duration": 60 },
    { "id": "a54", "title": "公園で自転車練習",            "tags": ["outdoor","kids","active"],     "duration": 90 },
    { "id": "a55", "title": "子どもとクッキング（サンドイッチ）","tags": ["indoor","kids","food"],  "duration": 50 },
    { "id": "a56", "title": "親子ヨガ",                    "tags": ["indoor","kids","refresh"],     "duration": 40 },
    { "id": "a57", "title": "近所の川で水遊び",            "tags": ["outdoor","kids","refresh"],    "duration": 70 },
    { "id": "a58", "title": "子どもとジブリ美術館めぐり",  "tags": ["indoor","kids","art"],         "duration": 120 },
    { "id": "a59", "title": "親子でジグソーパズル",        "tags": ["indoor","kids","relax"],       "duration": 60 },
    { "id": "a60", "title": "家庭菜園で収穫体験",          "tags": ["outdoor","kids","nature"],     "duration": 80 },
    { "id": "a61", "title": "公園で凧あげ",                "tags": ["outdoor","kids","refresh"],    "duration": 50 },
    { "id": "a62", "title": "科学館で工作ワークショップ",  "tags": ["indoor","kids","learning"],    "duration": 90 },
    { "id": "a63", "title": "親子でボードゲーム大会",      "tags": ["indoor","kids","relax"],       "duration": 100 },
    { "id": "a64", "title": "親子でキャンプごっこ（室内）","tags": ["indoor","kids","budget"],      "duration": 70 },
    { "id": "a65", "title": "公園でシャボン玉大会",        "tags": ["outdoor","kids","refresh"],    "duration": 30 },
    { "id": "a66", "title": "親子でお絵描き大会",          "tags": ["indoor","kids","art"],         "duration": 45 },
    { "id": "a67", "title": "プールで水泳練習",            "tags": ["outdoor","kids","active"],     "duration": 90 },
    { "id": "a68", "title": "親子でパンケーキ作り",        "tags": ["indoor","kids","food"],        "duration": 60 },
    { "id": "a69", "title": "森でどんぐり拾い",            "tags": ["outdoor","kids","nature"],     "duration": 40 },
    { "id": "a70", "title": "親子で映画鑑賞（アニメ）",    "tags": ["indoor","kids","relax"],       "duration": 100 },
    { "id": "a71", "title": "カフェで読書タイム",              "tags": ["indoor","solo","relax"],      "duration": 90 },
    { "id": "a72", "title": "美術館をゆっくり巡る",            "tags": ["indoor","solo","art"],        "duration": 120 },
    { "id": "a73", "title": "映画館で映画鑑賞",                "tags": ["indoor","solo","relax"],      "duration": 120 },
    { "id": "a74", "title": "図書館で調べもの",                "tags": ["indoor","solo","learning"],   "duration": 60 },
    { "id": "a75", "title": "お気に入りの公園を散歩",          "tags": ["outdoor","solo","refresh"],   "duration": 40 },
    { "id": "a76", "title": "ランニングコースを開拓",          "tags": ["outdoor","solo","health"],    "duration": 50 },
    { "id": "a77", "title": "ジムで筋トレ",                    "tags": ["indoor","solo","health"],     "duration": 70 },
    { "id": "a78", "title": "サウナで整う",                    "tags": ["indoor","solo","relax"],      "duration": 60 },
    { "id": "a79", "title": "ノートに目標や夢を書き出す",      "tags": ["indoor","solo","achievement"],"duration": 45 },
    { "id": "a80", "title": "資格試験の勉強",                  "tags": ["indoor","solo","learning"],   "duration": 120 },
    { "id": "a81", "title": "ショッピングモールでウィンドウショッピング", "tags": ["indoor","solo","refresh"], "duration": 90 },
    { "id": "a82", "title": "温泉でのんびり",                  "tags": ["indoor","solo","relax"],      "duration": 150 },
    { "id": "a83", "title": "美味しいお店を開拓（ひとりランチ）", "tags": ["indoor","solo","food"],     "duration": 70 },
    { "id": "a84", "title": "街中で写真撮影散歩",              "tags": ["outdoor","solo","hobby"],     "duration": 80 },
    { "id": "a85", "title": "お寺や神社で参拝",                "tags": ["outdoor","solo","refresh"],   "duration": 40 },
    { "id": "a86", "title": "おうちで映画マラソン",            "tags": ["indoor","solo","relax"],      "duration": 180 },
    { "id": "a87", "title": "ピアノやギターの練習",            "tags": ["indoor","solo","hobby"],      "duration": 60 },
    { "id": "a88", "title": "カラオケでひとり熱唱",            "tags": ["indoor","solo","stress"],     "duration": 90 },
    { "id": "a89", "title": "日記やブログ執筆",                "tags": ["indoor","solo","hobby"],      "duration": 60 },
    { "id": "a90", "title": "美味しいコーヒーを淹れて味わう",  "tags": ["indoor","solo","relax"],      "duration": 30 },
    { "id": "a91", "title": "ひとりカラオケボックスで練習",    "tags": ["indoor","solo","fun"],        "duration": 80 },
    { "id": "a92", "title": "新しいプログラミングを学ぶ",      "tags": ["indoor","solo","learning"],   "duration": 100 },
    { "id": "a93", "title": "ひとり旅の計画を立てる",          "tags": ["indoor","solo","experience"], "duration": 60 },
    { "id": "a94", "title": "公園でピクニックランチ",          "tags": ["outdoor","solo","refresh"],   "duration": 70 },
    { "id": "a95", "title": "展望台で夜景を眺める",            "tags": ["outdoor","solo","luxury"],    "duration": 90 },
    { "id": "a96", "title": "陶芸やクラフト体験教室",          "tags": ["indoor","solo","craft"],      "duration": 120 },
    { "id": "a97", "title": "古着屋を巡る",                    "tags": ["indoor","solo","hobby"],      "duration": 80 },
    { "id": "a98", "title": "街歩きしながら写真撮影",          "tags": ["outdoor","solo","art"],       "duration": 60 },
    { "id": "a99", "title": "ひとり居酒屋でしっぽり",          "tags": ["indoor","solo","relax"],      "duration": 100 },
    { "id": "a100","title": "好きな本をカフェで書き写す",      "tags": ["indoor","solo","learning"],   "duration": 80 },
    { "id": "a101", "title": "高級ホテルのアフタヌーンティー",       "tags": ["indoor","luxury","food"],     "duration": 120 },
    { "id": "a102", "title": "星付きレストランでディナー",           "tags": ["indoor","luxury","food"],     "duration": 150 },
    { "id": "a103", "title": "高層ホテルで宿泊ステイケーション",     "tags": ["indoor","luxury","relax"],    "duration": 1440 },
    { "id": "a104", "title": "スパで贅沢エステ体験",                 "tags": ["indoor","luxury","relax"],    "duration": 180 },
    { "id": "a105", "title": "温泉旅館で会席料理と温泉満喫",         "tags": ["indoor","luxury","relax"],    "duration": 1440 },
    { "id": "a106", "title": "豪華客船クルーズ",                     "tags": ["outdoor","luxury","experience"], "duration": 2880 },
    { "id": "a107", "title": "シェフズテーブルで特別コース",         "tags": ["indoor","luxury","food"],     "duration": 180 },
    { "id": "a108", "title": "高級ワインバーでテイスティング",       "tags": ["indoor","luxury","food"],     "duration": 120 },
    { "id": "a109", "title": "夜景が見えるホテルバーで一杯",         "tags": ["indoor","luxury","relax"],    "duration": 90 },
    { "id": "a110", "title": "ジャズクラブで生演奏を楽しむ",         "tags": ["indoor","luxury","art"],      "duration": 120 },
    { "id": "a111", "title": "ヘリコプター遊覧飛行",                 "tags": ["outdoor","luxury","experience"], "duration": 60 },
    { "id": "a112", "title": "高級リゾートでゴルフ",                 "tags": ["outdoor","luxury","active"],  "duration": 240 },
    { "id": "a113", "title": "リムジンでナイトドライブ",             "tags": ["outdoor","luxury","experience"], "duration": 90 },
    { "id": "a114", "title": "オーケストラコンサート鑑賞",           "tags": ["indoor","luxury","art"],      "duration": 150 },
    { "id": "a115", "title": "オペラ観劇",                           "tags": ["indoor","luxury","art"],      "duration": 180 },
    { "id": "a116", "title": "バレエ公演を観る",                     "tags": ["indoor","luxury","art"],      "duration": 150 },
    { "id": "a117", "title": "高級旅館の露天風呂でリラックス",       "tags": ["outdoor","luxury","relax"],   "duration": 180 },
    { "id": "a118", "title": "シャンパン付きサンセットクルーズ",     "tags": ["outdoor","luxury","refresh"], "duration": 120 },
    { "id": "a119", "title": "高級寿司カウンターでおまかせコース",   "tags": ["indoor","luxury","food"],     "duration": 120 },
    { "id": "a120", "title": "和牛専門店で鉄板焼ディナー",           "tags": ["indoor","luxury","food"],     "duration": 120 },
    { "id": "a121", "title": "高級ホテルのルーフトップバー",         "tags": ["indoor","luxury","relax"],    "duration": 120 },
    { "id": "a122", "title": "高級ブランド街でショッピング",         "tags": ["outdoor","luxury","hobby"],   "duration": 180 },
    { "id": "a123", "title": "リゾートホテルでプライベートビーチ",   "tags": ["outdoor","luxury","relax"],   "duration": 300 },
    { "id": "a124", "title": "高級旅館の懐石料理ランチ",             "tags": ["indoor","luxury","food"],     "duration": 120 },
    { "id": "a125", "title": "夜景ディナークルーズ",                 "tags": ["outdoor","luxury","food"],    "duration": 180 },
    { "id": "a126", "title": "一流ホテルのプールで遊ぶ",             "tags": ["indoor","luxury","refresh"],  "duration": 180 },
    { "id": "a127", "title": "会員制ラウンジでリラックス",           "tags": ["indoor","luxury","relax"],    "duration": 90 },
    { "id": "a128", "title": "シャンパンバーで乾杯",                 "tags": ["indoor","luxury","food"],     "duration": 120 },
    { "id": "a129", "title": "プライベートジェット体験",             "tags": ["outdoor","luxury","experience"], "duration": 180 },
    { "id": "a130", "title": "高級ホテルのルームサービス満喫",       "tags": ["indoor","luxury","food"],     "duration": 120 },
    { "id": "a131", "title": "豪華列車の旅",                         "tags": ["outdoor","luxury","experience"], "duration": 1440 },
    { "id": "a132", "title": "五つ星ホテルのスイート宿泊",           "tags": ["indoor","luxury","relax"],    "duration": 1440 },
    { "id": "a133", "title": "ワイン農園でテイスティングツアー",     "tags": ["outdoor","luxury","food"],    "duration": 180 },
    { "id": "a134", "title": "高級シガーバーでリラックス",           "tags": ["indoor","luxury","relax"],    "duration": 90 },
    { "id": "a135", "title": "高級ホテルでモーニングブッフェ",       "tags": ["indoor","luxury","food"],     "duration": 90 },
    { "id": "a136", "title": "伝統芸能（能・狂言）観賞",             "tags": ["indoor","luxury","art"],      "duration": 120 },
    { "id": "a137", "title": "プレミアム映画館で特別シート鑑賞",     "tags": ["indoor","luxury","art"],      "duration": 150 },
    { "id": "a138", "title": "一流シェフによる出張ディナー",         "tags": ["indoor","luxury","food"],     "duration": 180 },
    { "id": "a139", "title": "高級ホテルのクラブラウンジで休憩",     "tags": ["indoor","luxury","relax"],    "duration": 120 },
    { "id": "a140", "title": "VIPシートでスポーツ観戦",              "tags": ["outdoor","luxury","active"],  "duration": 150 },
    { "id": "a141", "title": "高級ホテルのバーでジャズナイト",       "tags": ["indoor","luxury","art"],      "duration": 120 },
    { "id": "a142", "title": "プライベートヨットで日帰りクルーズ",   "tags": ["outdoor","luxury","experience"], "duration": 480 },
    { "id": "a143", "title": "スイートルームでルームスパ体験",       "tags": ["indoor","luxury","relax"],    "duration": 150 },
    { "id": "a144", "title": "高級料亭で会席料理",                   "tags": ["indoor","luxury","food"],     "duration": 150 },
    { "id": "a145", "title": "シャンパン付きクラシック演奏会",       "tags": ["indoor","luxury","art"],      "duration": 150 },
    { "id": "a146", "title": "空港ラウンジで贅沢なひととき",         "tags": ["indoor","luxury","relax"],    "duration": 90 },
    { "id": "a147", "title": "高級ホテルの鉄板焼ランチ",             "tags": ["indoor","luxury","food"],     "duration": 120 },
    { "id": "a148", "title": "スパリゾートで1日リラックス",         "tags": ["indoor","luxury","relax"],    "duration": 360 },
    { "id": "a149", "title": "海外リゾート旅行（短期）",             "tags": ["outdoor","luxury","experience"], "duration": 4320 },
    { "id": "a150", "title": "星空の下でグランピング",               "tags": ["outdoor","luxury","nature"],  "duration": 720 },
    { "id": "a151", "title": "英会話スクールでレッスン",             "tags": ["indoor","learning","achievement"], "duration": 90 },
    { "id": "a152", "title": "プログラミング学習サイトで勉強",       "tags": ["indoor","learning","hobby"],       "duration": 120 },
    { "id": "a153", "title": "資格試験の過去問演習",                 "tags": ["indoor","learning","achievement"], "duration": 120 },
    { "id": "a154", "title": "オンライン講座で新スキル習得",         "tags": ["indoor","learning","hobby"],       "duration": 90 },
    { "id": "a155", "title": "読書会でインプットと交流",             "tags": ["indoor","learning","talk"],        "duration": 120 },
    { "id": "a156", "title": "ビジネス書を要約してノート化",         "tags": ["indoor","learning","achievement"], "duration": 60 },
    { "id": "a157", "title": "ヨガクラスで心身を整える",             "tags": ["indoor","health","selfcare"],      "duration": 60 },
    { "id": "a158", "title": "ランニングで体力づくり",               "tags": ["outdoor","health","achievement"],  "duration": 50 },
    { "id": "a159", "title": "ジムでパーソナルトレーニング",         "tags": ["indoor","health","achievement"],   "duration": 70 },
    { "id": "a160", "title": "パブリックスピーキングの練習",         "tags": ["indoor","learning","achievement"], "duration": 60 },
    { "id": "a161", "title": "日記を書いて自己分析",                 "tags": ["indoor","learning","selfcare"],    "duration": 30 },
    { "id": "a162", "title": "TOEIC模試にチャレンジ",                "tags": ["indoor","learning","achievement"], "duration": 120 },
    { "id": "a163", "title": "写経で集中力を高める",                 "tags": ["indoor","learning","relax"],       "duration": 45 },
    { "id": "a164", "title": "オンライン英会話で外国人と会話",       "tags": ["indoor","learning","hobby"],       "duration": 50 },
    { "id": "a165", "title": "新しい料理レシピを練習",               "tags": ["indoor","learning","hobby"],       "duration": 70 },
    { "id": "a166", "title": "自分史やエッセイを書いてみる",         "tags": ["indoor","learning","selfcare"],    "duration": 80 },
    { "id": "a167", "title": "マインドフルネス瞑想",                 "tags": ["indoor","health","relax"],         "duration": 30 },
    { "id": "a168", "title": "速読トレーニング",                     "tags": ["indoor","learning","achievement"], "duration": 40 },
    { "id": "a169", "title": "美文字練習（ペン字・書道）",           "tags": ["indoor","learning","hobby"],       "duration": 60 },
    { "id": "a170", "title": "ボイトレで発声練習",                   "tags": ["indoor","learning","hobby"],       "duration": 50 },
    { "id": "a171", "title": "キャリアプランを書き出す",             "tags": ["indoor","learning","achievement"], "duration": 60 },
    { "id": "a172", "title": "Excelやデータ分析を学ぶ",              "tags": ["indoor","learning","achievement"], "duration": 90 },
    { "id": "a173", "title": "プチ留学の情報収集",                   "tags": ["indoor","learning","experience"],  "duration": 80 },
    { "id": "a174", "title": "投資や資産運用の勉強",                 "tags": ["indoor","learning","achievement"], "duration": 100 },
    { "id": "a175", "title": "ポッドキャストで自己啓発",             "tags": ["indoor","learning","relax"],       "duration": 45 },
    { "id": "a176", "title": "自己紹介プレゼン資料を作る",           "tags": ["indoor","learning","achievement"], "duration": 70 },
    { "id": "a177", "title": "手帳に未来の計画を立てる",             "tags": ["indoor","learning","selfcare"],    "duration": 60 },
    { "id": "a178", "title": "オンライン資格講座の受講",             "tags": ["indoor","learning","achievement"], "duration": 90 },
    { "id": "a179", "title": "TEDトークを視聴して学ぶ",              "tags": ["indoor","learning","hobby"],       "duration": 40 },
    { "id": "a180", "title": "日本史の史跡を巡る",                   "tags": ["outdoor","learning","experience"], "duration": 150 },
    { "id": "a181", "title": "科学館で大人向け展示を見学",           "tags": ["indoor","learning","experience"], "duration": 120 },
    { "id": "a182", "title": "写真撮影スキルを磨く練習",             "tags": ["outdoor","learning","hobby"],     "duration": 90 },
    { "id": "a183", "title": "イラスト練習（デジタルorアナログ）",   "tags": ["indoor","learning","hobby"],      "duration": 100 },
    { "id": "a184", "title": "デザインソフトを学ぶ",                 "tags": ["indoor","learning","achievement"], "duration": 120 },
    { "id": "a185", "title": "外国語のリスニング練習",               "tags": ["indoor","learning","hobby"],       "duration": 60 },
    { "id": "a186", "title": "プログラミングで小アプリ開発",         "tags": ["indoor","learning","achievement"], "duration": 120 },
    { "id": "a187", "title": "ビジネスマナー講座を受ける",           "tags": ["indoor","learning","selfcare"],    "duration": 80 },
    { "id": "a188", "title": "体験型ワークショップに参加",           "tags": ["indoor","learning","experience"], "duration": 120 },
    { "id": "a189", "title": "アートセラピーを受ける",               "tags": ["indoor","learning","relax"],       "duration": 90 },
    { "id": "a190", "title": "スピーチコンテストに挑戦",             "tags": ["indoor","learning","achievement"], "duration": 150 },
    { "id": "a191", "title": "お菓子作り教室に参加",                 "tags": ["indoor","learning","hobby"],       "duration": 120 },
    { "id": "a192", "title": "ダンスレッスンで基礎練習",             "tags": ["indoor","learning","hobby"],       "duration": 90 },
    { "id": "a193", "title": "外国語の作文練習",                     "tags": ["indoor","learning","achievement"], "duration": 60 },
    { "id": "a194", "title": "哲学書を読み考察メモを書く",           "tags": ["indoor","learning","achievement"], "duration": 90 },
    { "id": "a195", "title": "書道体験で集中する",                   "tags": ["indoor","learning","relax"],       "duration": 70 },
    { "id": "a196", "title": "パーソナルカラー診断を受ける",         "tags": ["indoor","learning","selfcare"],    "duration": 60 },
    { "id": "a197", "title": "姿勢改善ストレッチ講座",               "tags": ["indoor","health","achievement"],   "duration": 50 },
    { "id": "a198", "title": "発声・朗読の練習",                     "tags": ["indoor","learning","hobby"],       "duration": 60 },
    { "id": "a199", "title": "ビジョンボードを作成する",             "tags": ["indoor","learning","selfcare"],    "duration": 80 },
    { "id": "a200", "title": "自己分析ワークブックに取り組む",       "tags": ["indoor","learning","achievement"], "duration": 70 },
    { "id": "a201", "title": "VRアーケードで没入体験",                 "tags": ["indoor","experience","fun"],           "duration": 60  },
    { "id": "a202", "title": "ボルダリング体験レッスン",               "tags": ["indoor","experience","active"],        "duration": 90  },
    { "id": "a203", "title": "アーチェリー体験",                       "tags": ["indoor","experience","active"],        "duration": 75  },
    { "id": "a204", "title": "サルサ/ラテンダンス初級クラス",          "tags": ["indoor","experience","fun"],           "duration": 90  },
    { "id": "a205", "title": "茶道体験（お点前を学ぶ）",               "tags": ["indoor","experience","learning","art"],"duration": 80  },
    { "id": "a206", "title": "華道（いけばな）体験",                    "tags": ["indoor","experience","art"],           "duration": 70  },
    { "id": "a207", "title": "ガラス吹きワークショップ",               "tags": ["indoor","experience","craft"],         "duration": 120 },
    { "id": "a208", "title": "革小物づくり体験",                       "tags": ["indoor","experience","craft"],         "duration": 120 },
    { "id": "a209", "title": "金継ぎ体験（器の修復）",                 "tags": ["indoor","experience","craft"],         "duration": 120 },
    { "id": "a210", "title": "カヤック体験",                           "tags": ["outdoor","experience","active","nature"], "duration": 120 },
    { "id": "a211", "title": "SUP（スタンドアップパドル）体験",        "tags": ["outdoor","experience","active","nature"], "duration": 120 },
    { "id": "a212", "title": "乗馬入門レッスン",                        "tags": ["outdoor","experience","active","nature"], "duration": 90  },
    { "id": "a213", "title": "陶芸ろくろ体験",                          "tags": ["indoor","experience","craft"],         "duration": 120 },
    { "id": "a214", "title": "染物（藍染め）体験",                      "tags": ["indoor","experience","craft"],         "duration": 90  },
    { "id": "a215", "title": "和菓子づくり体験",                        "tags": ["indoor","experience","food"],          "duration": 90  },
    { "id": "a216", "title": "バリスタ体験（ラテアート）",              "tags": ["indoor","experience","food","learning"], "duration": 75  },
    { "id": "a217", "title": "クラフトビール醸造所ツアー",             "tags": ["indoor","experience","food"],          "duration": 90  },
    { "id": "a218", "title": "ワイナリー見学とテイスティング",          "tags": ["outdoor","experience","food","nature"], "duration": 120 },
    { "id": "a219", "title": "エスケープルーム（脱出ゲーム）",          "tags": ["indoor","experience","fun"],           "duration": 60  },
    { "id": "a220", "title": "ボイスドラマ収録体験",                    "tags": ["indoor","experience","art"],           "duration": 90  },
    { "id": "a221", "title": "陶磁器の絵付け体験",                      "tags": ["indoor","experience","craft","art"],   "duration": 100 },
    { "id": "a222", "title": "カリグラフィー体験（西洋書道）",          "tags": ["indoor","experience","art","learning"],"duration": 80  },
    { "id": "a223", "title": "フェンシング体験レッスン",                "tags": ["indoor","experience","active"],        "duration": 90  },
    { "id": "a224", "title": "ボートレース観戦デビュー",                "tags": ["outdoor","experience","fun"],          "duration": 120 },
    { "id": "a225", "title": "和太鼓体験ワークショップ",                "tags": ["indoor","experience","active","art"],  "duration": 70  },
    { "id": "a226", "title": "吹きガラスのペーパーウェイト作り",        "tags": ["indoor","experience","craft"],         "duration": 90  },
    { "id": "a227", "title": "木工でまな板を作る",                      "tags": ["indoor","experience","craft"],         "duration": 120 },
    { "id": "a228", "title": "スカイダイビング体験",                    "tags": ["outdoor","experience","active"],       "duration": 180 },
    { "id": "a229", "title": "熱気球フライト体験",                      "tags": ["outdoor","experience","refresh","nature"], "duration": 180 },
    { "id": "a230", "title": "洞窟探検（ケイビング）体験",              "tags": ["outdoor","experience","active","nature"], "duration": 180 },
    { "id": "a231", "title": "スタンドアップコメディ観賞デビュー",      "tags": ["indoor","experience","fun","art"],     "duration": 90  },
    { "id": "a232", "title": "ボディペインティング体験",                "tags": ["indoor","experience","art"],           "duration": 60  },
    { "id": "a233", "title": "都市養蜂見学（はちみつ搾り）",            "tags": ["outdoor","experience","learning","nature"], "duration": 90  },
    { "id": "a234", "title": "カプセルホテル初体験ステイ",              "tags": ["indoor","experience","refresh"],       "duration": 720 },
    { "id": "a235", "title": "ゲストハウスに泊まって交流",               "tags": ["indoor","experience","talk"],          "duration": 720 },
    { "id": "a236", "title": "異文化料理教室（エスニック）",            "tags": ["indoor","experience","food","learning"], "duration": 120 },
    { "id": "a237", "title": "ボランティア体験（清掃/配膳等）",         "tags": ["outdoor","experience","achievement"],  "duration": 120 },
    { "id": "a238", "title": "ラジオ公開収録を見学",                    "tags": ["indoor","experience","art"],           "duration": 90  },
    { "id": "a239", "title": "陶器市・クラフトフェアに初参戦",          "tags": ["outdoor","experience","walk","art"],   "duration": 120 },
    { "id": "a240", "title": "野外シネマで映画鑑賞",                    "tags": ["outdoor","experience","art","refresh"], "duration": 120 },
    { "id": "a241", "title": "パルクール入門クラス",                    "tags": ["outdoor","experience","active"],       "duration": 90  },
    { "id": "a242", "title": "ゴスペルクワイア体験",                    "tags": ["indoor","experience","art","fun"],     "duration": 100 },
    { "id": "a243", "title": "手作り香水ワークショップ",                "tags": ["indoor","experience","craft"],         "duration": 80  },
    { "id": "a244", "title": "カメラのレンタルでフィルム撮影に挑戦",    "tags": ["outdoor","experience","hobby"],        "duration": 120 },
    { "id": "a245", "title": "書道体験（半紙から作品制作まで）",        "tags": ["indoor","experience","art","learning"], "duration": 90  },
    { "id": "a246", "title": "街のアートツアー（壁画/ギャラリー）",     "tags": ["outdoor","experience","art","walk"],   "duration": 120 },
    { "id": "a247", "title": "セグウェイ体験ツアー",                    "tags": ["outdoor","experience","active"],       "duration": 60  },
    { "id": "a248", "title": "ミニ四駆/RCカー体験会",                   "tags": ["indoor","experience","hobby"],         "duration": 80  },
    { "id": "a249", "title": "ゼロウェイストショップで量り売り体験",    "tags": ["indoor","experience","learning"],      "duration": 60  },
    { "id": "a250", "title": "ナイトハイク（星空ガイド付き）",          "tags": ["outdoor","experience","nature","refresh"], "duration": 150 } ,
    { "id": "a301", "title": "キッチンのシンクを徹底掃除",            "tags": ["indoor","clean","home"], "duration": 45 },
    { "id": "a302", "title": "冷蔵庫の中を整理＆拭き掃除",            "tags": ["indoor","clean","home"], "duration": 40 },
    { "id": "a303", "title": "洗面所の鏡と蛇口をピカピカにする",       "tags": ["indoor","clean","home"], "duration": 30 },
    { "id": "a304", "title": "クローゼットの衣替え",                  "tags": ["indoor","clean","organize"], "duration": 90 },
    { "id": "a305", "title": "不要な服を仕分けして寄付や処分",        "tags": ["indoor","clean","organize"], "duration": 60 },
    { "id": "a306", "title": "靴箱を整理して靴を磨く",                "tags": ["indoor","clean","home"], "duration": 50 },
    { "id": "a307", "title": "ベランダの掃き掃除＆プランター整理",     "tags": ["outdoor","clean","nature"], "duration": 60 },
    { "id": "a308", "title": "玄関のたたきを拭き掃除",                "tags": ["indoor","clean","home"], "duration": 20 },
    { "id": "a309", "title": "バスルームのカビ取り",                  "tags": ["indoor","clean","home"], "duration": 60 },
    { "id": "a310", "title": "トイレの徹底掃除",                       "tags": ["indoor","clean","home"], "duration": 40 },
  
    { "id": "a311", "title": "床を水拭きしてリフレッシュ",             "tags": ["indoor","clean","refresh"], "duration": 45 },
    { "id": "a312", "title": "本棚を整理して不要本を仕分け",           "tags": ["indoor","clean","organize"], "duration": 70 },
    { "id": "a313", "title": "引き出し1つだけ整理チャレンジ",          "tags": ["indoor","clean","organize"], "duration": 20 },
    { "id": "a314", "title": "洗濯機の槽をクリーニング",               "tags": ["indoor","clean","home"], "duration": 90 },
    { "id": "a315", "title": "布団を干してシーツを交換",               "tags": ["indoor","clean","refresh"], "duration": 50 },
    { "id": "a316", "title": "窓ガラスとサッシの掃除",                 "tags": ["indoor","clean","refresh"], "duration": 60 },
    { "id": "a317", "title": "電子レンジの中を掃除",                   "tags": ["indoor","clean","home"], "duration": 20 },
    { "id": "a318", "title": "ゴミ箱を丸洗いして消臭",                 "tags": ["indoor","clean","home"], "duration": 30 },
    { "id": "a319", "title": "調味料を整理してラベル付け",             "tags": ["indoor","clean","organize"], "duration": 45 },
    { "id": "a320", "title": "食器棚の整理＆食器拭き",                 "tags": ["indoor","clean","home"], "duration": 60 },
  
    { "id": "a321", "title": "ベッドの下を掃除して整理",               "tags": ["indoor","clean","home"], "duration": 40 },
    { "id": "a322", "title": "コードやケーブルをまとめて整える",       "tags": ["indoor","clean","organize"], "duration": 30 },
    { "id": "a323", "title": "日用品ストックの棚卸し",                 "tags": ["indoor","clean","organize"], "duration": 25 },
    { "id": "a324", "title": "レシートや書類を整理",                   "tags": ["indoor","clean","organize"], "duration": 45 },
    { "id": "a325", "title": "郵便物・手紙を仕分けて保存",             "tags": ["indoor","clean","organize"], "duration": 30 },
    { "id": "a326", "title": "玄関マットを洗濯して干す",               "tags": ["indoor","clean","refresh"], "duration": 30 },
    { "id": "a327", "title": "カーテンを洗濯してリフレッシュ",         "tags": ["indoor","clean","refresh"], "duration": 90 },
    { "id": "a328", "title": "照明のほこりを拭き取る",                 "tags": ["indoor","clean","home"], "duration": 30 },
    { "id": "a329", "title": "観葉植物の葉を拭いて整える",             "tags": ["indoor","clean","nature"], "duration": 20 },
    { "id": "a330", "title": "洗濯物をたたんで仕舞う",                 "tags": ["indoor","clean","home"], "duration": 25 },
  
    { "id": "a331", "title": "アイロンがけをまとめてやる",             "tags": ["indoor","clean","home"], "duration": 60 },
    { "id": "a332", "title": "靴下やタオルを整理整頓",                 "tags": ["indoor","clean","organize"], "duration": 20 },
    { "id": "a333", "title": "水筒やボトルを漂白洗浄",                 "tags": ["indoor","clean","home"], "duration": 40 },
    { "id": "a334", "title": "エアコンのフィルター掃除",               "tags": ["indoor","clean","refresh"], "duration": 40 },
    { "id": "a335", "title": "家計簿や家事リストを整える",             "tags": ["indoor","clean","organize","learning"], "duration": 60 },
    { "id": "a336", "title": "非常食の賞味期限を確認",                 "tags": ["indoor","clean","organize"], "duration": 20 },
    { "id": "a337", "title": "薬箱の中を整理して補充",                 "tags": ["indoor","clean","organize"], "duration": 25 },
    { "id": "a338", "title": "お気に入りの食器を磨く",                  "tags": ["indoor","clean","home"], "duration": 30 },
    { "id": "a339", "title": "布団圧縮袋に入れて収納",                 "tags": ["indoor","clean","organize"], "duration": 60 },
    { "id": "a340", "title": "季節の花を飾って部屋を整える",           "tags": ["indoor","clean","refresh","art"], "duration": 30 },
  
    { "id": "a341", "title": "デジタル写真を整理",                      "tags": ["indoor","clean","digital"], "duration": 60 },
    { "id": "a342", "title": "PCやスマホの不要ファイル削除",            "tags": ["indoor","clean","digital"], "duration": 45 },
    { "id": "a343", "title": "メールボックスの未読ゼロチャレンジ",      "tags": ["indoor","clean","digital"], "duration": 60 },
    { "id": "a344", "title": "クラウドのフォルダ整理",                  "tags": ["indoor","clean","digital"], "duration": 60 },
    { "id": "a345", "title": "SNSフォローを整理",                       "tags": ["indoor","clean","digital"], "duration": 40 },
    { "id": "a346", "title": "パスワードを整理・更新",                   "tags": ["indoor","clean","digital"], "duration": 50 },
    { "id": "a347", "title": "冷凍庫を整理して使い切る計画",            "tags": ["indoor","clean","home"], "duration": 40 },
    { "id": "a348", "title": "キッチンタイマーで15分片付けチャレンジ", "tags": ["indoor","clean","fun"], "duration": 15 },
    { "id": "a349", "title": "洗剤や掃除道具を補充して整える",         "tags": ["indoor","clean","home"], "duration": 20 },
    { "id": "a350", "title": "翌週の献立を考えて買い物リストを作成",   "tags": ["indoor","clean","organize","food"], "duration": 60 }   
  ]  